jupyterlab_data_mount/__init__.py
jupyterlab_data_mount/_version.py
jupyterlab_data_mount/handlers.py
jupyterlab_data_mount/tests/__init__.py
jupyterlab_data_mount/tests/test_handlers.py
jupyterlab_data_mount-1.0.0.data/data/etc/jupyter/jupyter_server_config.d/jupyterlab_data_mount.json
jupyterlab_data_mount-1.0.0.data/data/share/jupyter/labextensions/jupyterlab-data-mount/package.json
jupyterlab_data_mount-1.0.0.data/data/share/jupyter/labextensions/jupyterlab-data-mount/schemas/jupyterlab-data-mount/package.json.orig
jupyterlab_data_mount-1.0.0.data/data/share/jupyter/labextensions/jupyterlab-data-mount/schemas/jupyterlab-data-mount/plugin.json
jupyterlab_data_mount-1.0.0.data/data/share/jupyter/labextensions/jupyterlab-data-mount/static/293.bf9b4437283e682bbd37.js
jupyterlab_data_mount-1.0.0.data/data/share/jupyter/labextensions/jupyterlab-data-mount/static/293.bf9b4437283e682bbd37.js.LICENSE.txt
jupyterlab_data_mount-1.0.0.data/data/share/jupyter/labextensions/jupyterlab-data-mount/static/436.e53ea0bde96b841b49b3.js
jupyterlab_data_mount-1.0.0.data/data/share/jupyter/labextensions/jupyterlab-data-mount/static/436.e53ea0bde96b841b49b3.js.LICENSE.txt
jupyterlab_data_mount-1.0.0.data/data/share/jupyter/labextensions/jupyterlab-data-mount/static/533.32db51c93ed2f1ebd555.js
jupyterlab_data_mount-1.0.0.data/data/share/jupyter/labextensions/jupyterlab-data-mount/static/55.9ffb1e4fde4eeb34d2c1.js
jupyterlab_data_mount-1.0.0.data/data/share/jupyter/labextensions/jupyterlab-data-mount/static/55.9ffb1e4fde4eeb34d2c1.js.LICENSE.txt
jupyterlab_data_mount-1.0.0.data/data/share/jupyter/labextensions/jupyterlab-data-mount/static/666.d46a1a92c275cd91df3d.js
jupyterlab_data_mount-1.0.0.data/data/share/jupyter/labextensions/jupyterlab-data-mount/static/674.38fc2b81488b765317ca.js
jupyterlab_data_mount-1.0.0.data/data/share/jupyter/labextensions/jupyterlab-data-mount/static/674.38fc2b81488b765317ca.js.LICENSE.txt
jupyterlab_data_mount-1.0.0.dist-info/METADATA
jupyterlab_data_mount-1.0.0.dist-info/WHEEL
jupyterlab_data_mount-1.0.0.dist-info/licenses/LICENSE
jupyterlab_data_mount-1.0.0.dist-info/RECORD
